scrapy_zenrows/README.md
scrapy_zenrows/__init__.py
scrapy_zenrows/__version__.py
scrapy_zenrows/api_key_handler.py
scrapy_zenrows/middleware.py
scrapy_zenrows/retry.py
scrapy_zenrows/zenrows_request.py
scrapy_zenrows_middleware-1.1.2.dist-info/licenses/LICENSE
scrapy_zenrows_middleware-1.1.2.dist-info/METADATA
scrapy_zenrows_middleware-1.1.2.dist-info/WHEEL
scrapy_zenrows_middleware-1.1.2.dist-info/top_level.txt
scrapy_zenrows_middleware-1.1.2.dist-info/RECORD
