Metadata-Version: 2.4
Name: scrapy-zenrows-middleware
Version: 1.1.2
Summary: A Scrapy middleware for accessing ZenRows Scraper API with minimal setup.
Home-page: https://github.com/ZenRows/scrapy-zenrows-middleware
Author: Idowu Omisola and Yuvraj Chandra
Author-email: Idowu Omisola and Yuvraj Chandra <support@zenrows.com>
License: MIT
Project-URL: Homepage, https://github.com/ZenRows/scrapy-zenrows-middleware
Project-URL: Documentation, https://docs.zenrows.com/scraping-api/integrations/scrapy
Project-URL: Repository, https://github.com/ZenRows/scrapy-zenrows-middleware
Classifier: Programming Language :: Python :: 3
Classifier: Programming Language :: Python :: 3.8
Classifier: Programming Language :: Python :: 3.9
Classifier: Programming Language :: Python :: 3.10
Classifier: Programming Language :: Python :: 3.11
Classifier: Programming Language :: Python :: 3.12
Classifier: Programming Language :: Python :: 3.13
Classifier: Operating System :: OS Independent
Classifier: Framework :: Scrapy
Requires-Python: >=3.8
License-File: LICENSE
Requires-Dist: scrapy>=2.0
Dynamic: author
Dynamic: home-page
Dynamic: license-file
Dynamic: requires-python
